<annotation>
	<folder>2011-1</folder>
	<filename>1jm101067y.pdf_2.jpg</filename>
	<path>C:\Users\YML\Downloads\2011-1\1jm101067y.pdf_2.jpg</path>
	<source>
		<database>Unknown</database>
	</source>
	<size>
		<width>1266</width>
		<height>1669</height>
		<depth>3</depth>
	</size>
	<segmented>0</segmented>
	<object>
		<name>exist_molecular</name>
		<pose>Unspecified</pose>
		<truncated>0</truncated>
		<difficult>0</difficult>
		<bndbox>
			<xmin>103</xmin>
			<ymin>592</ymin>
			<xmax>303</xmax>
			<ymax>730</ymax>
		</bndbox>
	</object>
	<object>
		<name>exist_molecular</name>
		<pose>Unspecified</pose>
		<truncated>0</truncated>
		<difficult>0</difficult>
		<bndbox>
			<xmin>287</xmin>
			<ymin>598</ymin>
			<xmax>470</xmax>
			<ymax>716</ymax>
		</bndbox>
	</object>
	<object>
		<name>exist_molecular</name>
		<pose>Unspecified</pose>
		<truncated>0</truncated>
		<difficult>0</difficult>
		<bndbox>
			<xmin>481</xmin>
			<ymin>570</ymin>
			<xmax>615</xmax>
			<ymax>730</ymax>
		</bndbox>
	</object>
	<object>
		<name>exist_molecular</name>
		<pose>Unspecified</pose>
		<truncated>0</truncated>
		<difficult>0</difficult>
		<bndbox>
			<xmin>260</xmin>
			<ymin>1334</ymin>
			<xmax>367</xmax>
			<ymax>1384</ymax>
		</bndbox>
	</object>
	<object>
		<name>exist_molecular</name>
		<pose>Unspecified</pose>
		<truncated>0</truncated>
		<difficult>0</difficult>
		<bndbox>
			<xmin>425</xmin>
			<ymin>1313</ymin>
			<xmax>581</xmax>
			<ymax>1442</ymax>
		</bndbox>
	</object>
	<object>
		<name>exist_molecular</name>
		<pose>Unspecified</pose>
		<truncated>0</truncated>
		<difficult>0</difficult>
		<bndbox>
			<xmin>637</xmin>
			<ymin>1310</ymin>
			<xmax>758</xmax>
			<ymax>1438</ymax>
		</bndbox>
	</object>
	<object>
		<name>exist_molecular</name>
		<pose>Unspecified</pose>
		<truncated>0</truncated>
		<difficult>0</difficult>
		<bndbox>
			<xmin>842</xmin>
			<ymin>1311</ymin>
			<xmax>982</xmax>
			<ymax>1437</ymax>
		</bndbox>
	</object>
</annotation>
