<annotation>
	<folder>2010label_1</folder>
	<filename>1m100158v.pdf_2.jpg</filename>
	<path>C:\Users\Administrator.DESKTOP-1U2MF74\Desktop\2010label_1\1m100158v.pdf_2.jpg</path>
	<source>
		<database>Unknown</database>
	</source>
	<size>
		<width>1266</width>
		<height>1669</height>
		<depth>3</depth>
	</size>
	<segmented>0</segmented>
	<object>
		<name>exist_molecular</name>
		<pose>Unspecified</pose>
		<truncated>0</truncated>
		<difficult>0</difficult>
		<bndbox>
			<xmin>744</xmin>
			<ymin>1053</ymin>
			<xmax>871</xmax>
			<ymax>1155</ymax>
		</bndbox>
	</object>
	<object>
		<name>exist_molecular</name>
		<pose>Unspecified</pose>
		<truncated>0</truncated>
		<difficult>0</difficult>
		<bndbox>
			<xmin>944</xmin>
			<ymin>1051</ymin>
			<xmax>1082</xmax>
			<ymax>1145</ymax>
		</bndbox>
	</object>
	<object>
		<name>exist_molecular</name>
		<pose>Unspecified</pose>
		<truncated>0</truncated>
		<difficult>0</difficult>
		<bndbox>
			<xmin>897</xmin>
			<ymin>1229</ymin>
			<xmax>1118</xmax>
			<ymax>1374</ymax>
		</bndbox>
	</object>
	<object>
		<name>exist_molecular</name>
		<pose>Unspecified</pose>
		<truncated>0</truncated>
		<difficult>0</difficult>
		<bndbox>
			<xmin>728</xmin>
			<ymin>1307</ymin>
			<xmax>889</xmax>
			<ymax>1372</ymax>
		</bndbox>
	</object>
	<object>
		<name>exist_molecular</name>
		<pose>Unspecified</pose>
		<truncated>0</truncated>
		<difficult>0</difficult>
		<bndbox>
			<xmin>752</xmin>
			<ymin>539</ymin>
			<xmax>877</xmax>
			<ymax>629</ymax>
		</bndbox>
	</object>
	<object>
		<name>exist_molecular</name>
		<pose>Unspecified</pose>
		<truncated>0</truncated>
		<difficult>0</difficult>
		<bndbox>
			<xmin>578</xmin>
			<ymin>596</ymin>
			<xmax>666</xmax>
			<ymax>674</ymax>
		</bndbox>
	</object>
	<object>
		<name>exist_molecular</name>
		<pose>Unspecified</pose>
		<truncated>0</truncated>
		<difficult>0</difficult>
		<bndbox>
			<xmin>371</xmin>
			<ymin>367</ymin>
			<xmax>490</xmax>
			<ymax>469</ymax>
		</bndbox>
	</object>
	<object>
		<name>exist_molecular</name>
		<pose>Unspecified</pose>
		<truncated>0</truncated>
		<difficult>0</difficult>
		<bndbox>
			<xmin>777</xmin>
			<ymin>369</ymin>
			<xmax>909</xmax>
			<ymax>476</ymax>
		</bndbox>
	</object>
	<object>
		<name>exist_molecular</name>
		<pose>Unspecified</pose>
		<truncated>0</truncated>
		<difficult>0</difficult>
		<bndbox>
			<xmin>570</xmin>
			<ymin>362</ymin>
			<xmax>697</xmax>
			<ymax>477</ymax>
		</bndbox>
	</object>
	<object>
		<name>exist_molecular</name>
		<pose>Unspecified</pose>
		<truncated>0</truncated>
		<difficult>0</difficult>
		<bndbox>
			<xmin>747</xmin>
			<ymin>229</ymin>
			<xmax>837</xmax>
			<ymax>307</ymax>
		</bndbox>
	</object>
	<object>
		<name>exist_molecular</name>
		<pose>Unspecified</pose>
		<truncated>0</truncated>
		<difficult>0</difficult>
		<bndbox>
			<xmin>570</xmin>
			<ymin>169</ymin>
			<xmax>694</xmax>
			<ymax>257</ymax>
		</bndbox>
	</object>
</annotation>
